tail_envs/__init__.py
tail_envs-0.0.1.dist-info/LICENSE
tail_envs-0.0.1.dist-info/METADATA
tail_envs-0.0.1.dist-info/WHEEL
tail_envs-0.0.1.dist-info/top_level.txt
tail_envs-0.0.1.dist-info/RECORD
